spoofer/__init__.py
spoofer/listen.py
spoofer/spoofer.py
spoofer/utils.py
dns_spoofer-1.0.dist-info/LICENSE
dns_spoofer-1.0.dist-info/METADATA
dns_spoofer-1.0.dist-info/WHEEL
dns_spoofer-1.0.dist-info/entry_points.txt
dns_spoofer-1.0.dist-info/top_level.txt
dns_spoofer-1.0.dist-info/RECORD
