Metadata-Version: 2.1
Name: dns-spoofer
Version: 1.0
Summary: Spoof DNS queries over UDP
Home-page: https://github.com/kimbo/dns-spoofer
Author: Kimball Leavitt
Author-email: kimballleavitt@gmail.com
License: UNKNOWN
Platform: UNKNOWN
Requires-Dist: dnspython
